{"cameraMode":{"drawMode":0,"name":"Shaded","section":"Shading Mode"},"sceneLighting":false,"audioPlay":false,"sceneViewState":{"m_AlwaysRefresh":false,"showFog":true,"showSkybox":false,"showFlares":true,"showImageEffects":true,"showParticleSystems":true,"showVisualEffectGraphs":true,"m_FxEnabled":true},"in2DMode":false,"pivot":{"x":55.66878890991211,"y":21.01637840270996,"z":57.19032669067383},"rotation":{"x":0.01181408017873764,"y":0.9768421053886414,"z":-0.206986665725708,"w":0.05545150116086006},"size":4.872359275817871,"orthographic":false}